MANIFEST.in
README.md
setup.py
tls_middleware.py
django_tls_middleware.egg-info/PKG-INFO
django_tls_middleware.egg-info/SOURCES.txt
django_tls_middleware.egg-info/dependency_links.txt
django_tls_middleware.egg-info/top_level.txt