Metadata-Version: 1.0
Name: django-tls-middleware
Version: 0.1.1
Summary: TLS Middleware
Home-page: https://github.com/sekomy/django-tls-middleware
Author: Sekom Yazilim
Author-email: info@sekomyazilim.com.tr
License: MIT
Platform: any
